Workbook

Sheet Inputs
A1: Help Mobility — H2 2026 Growth Model • INPUTS (edit the blue cells)
A3: Baseline monthly revenue | B3: 100000 | C3: =direct sales + technical support + sales services + rental renewals (measured streams)
A4: Note: if $100k is PER stream (~$400k/mo), scale targets up ~4x. B2B + outside sales are additional and not yet measured.
A6: AVERAGE VALUES (editable)
A7: Avg insurance (AOB) deal value | B7: 1800
A8: Avg WSIB / VAC / NIHB deal value | B8: 2000
A9: Avg HVMP / Renovates accessibility job | B9: 6000
A10: Avg rental revenue per unit / month | B10: 250
A11: Avg recurring (resupply / PM) per account / month | B11: 120
A13: LEVER DRIVERS — monthly, at full H2 run-rate
A14: Lever / driver | C14: Conservative | D14: Base | E14: Stretch
A15: ODSP 100% conversion uplift ($/mo, direct) | B15: $/mo | C15: 1500 | D15: 3000 | E15: 5000
A16: Insurance AOB — new deals / month | B16: deals | C16: 5 | D16: 10 | E16: 22
A17: WSIB / VAC / NIHB — new deals / month | B17: deals | C17: 3 | D17: 7 | E17: 12
A18: HVMP / Renovates accessibility jobs / month | B18: jobs | C18: 2 | D18: 5 | E18: 12
A19: Hospital-at-Home — active rental units | B19: units | C19: 15 | D19: 35 | E19: 75
A20: Recurring accounts (resupply/PM/reactivation) | B20: accounts | C20: 40 | D20: 90 | E20: 150
A21: Referral engine uplift (% of baseline) | B21: % | C21: 0.08 | D21: 0.15 | E21: 0.25

Sheet Bridge
A1: Revenue Bridge • baseline → target (formulas; recompute when you edit Inputs)
A3: Lever | B3: Conservative | C3: Base | D3: Stretch
A4: ODSP 100% conversion | B4: =Inputs!C15 | C4: =Inputs!D15 | D4: =Inputs!E15
A5: Insurance AOB (new payers) | B5: =Inputs!C16*Inputs!$B$7 | C5: =Inputs!D16*Inputs!$B$7 | D5: =Inputs!E16*Inputs!$B$7
A6: WSIB / VAC / NIHB | B6: =Inputs!C17*Inputs!$B$8 | C6: =Inputs!D17*Inputs!$B$8 | D6: =Inputs!E17*Inputs!$B$8
A7: HVMP / Renovates (accessibility & mods) | B7: =Inputs!C18*Inputs!$B$9 | C7: =Inputs!D18*Inputs!$B$9 | D7: =Inputs!E18*Inputs!$B$9
A8: Hospital-at-Home rentals | B8: =Inputs!C19*Inputs!$B$10 | C8: =Inputs!D19*Inputs!$B$10 | D8: =Inputs!E19*Inputs!$B$10
A9: Recurring (resupply / PM / reactivation) | B9: =Inputs!C20*Inputs!$B$11 | C9: =Inputs!D20*Inputs!$B$11 | D9: =Inputs!E20*Inputs!$B$11
A10: Referral engine uplift | B10: =Inputs!C21*Inputs!$B$3 | C10: =Inputs!D21*Inputs!$B$3 | D10: =Inputs!E21*Inputs!$B$3
A11: Total incremental / month | B11: =SUM(B4:B10) | C11: =SUM(C4:C10) | D11: =SUM(D4:D10)
A12: Baseline / month | B12: =Inputs!$B$3 | C12: =Inputs!$B$3 | D12: =Inputs!$B$3
A13: TARGET monthly revenue | B13: =B11+B12 | C13: =C11+C12 | D13: =D11+D12
A14: × of baseline | B14: =B13/B12 | C14: =C13/C12 | D14: =D13/D12
A15: Annualized run-rate (×12) | B15: =B13*12 | C15: =C13*12 | D15: =D13*12
A17: Base case ~2.0x, Stretch ~3.0x on the measured streams. B2B + outside sales add on top.

Sheet H2_Ramp
A1: H2 2026 Monthly Ramp (Base scenario) • the path from 1x to ~2x run-rate
A3: Month | B3: Ramp % of full run-rate | C3: Modeled monthly revenue
A4: Jul | B4: 0.1 | C4: =Bridge!$C$12+Bridge!$C$11*B4
A5: Aug | B5: 0.25 | C5: =Bridge!$C$12+Bridge!$C$11*B5
A6: Sep | B6: 0.45 | C6: =Bridge!$C$12+Bridge!$C$11*B6
A7: Oct | B7: 0.65 | C7: =Bridge!$C$12+Bridge!$C$11*B7
A8: Nov | B8: 0.85 | C8: =Bridge!$C$12+Bridge!$C$11*B8
A9: Dec | B9: 1 | C9: =Bridge!$C$12+Bridge!$C$11*B9
A10: H2 total revenue | C10: =SUM(C4:C9)
A11: December run-rate, annualized | C11: =C9*12

Sheet KPIs
A1: KPI Dashboard — review weekly
A3: Metric | B3: Why it matters | C3: Owner
A4: Leads by source / referral sources active | B4: Top-of-funnel health | C4: Community Liaison
A5: % pipeline with verified funding | B5: Predicts conversion | C5: Funding & Intake desk
A6: Funding approval rate | B6: Revenue capture | C6: Funding & Intake desk
A7: Funding approval cycle time (days) | B7: Speed = cash + hospital trust | C7: Funding & Intake desk
A8: Denials logged + recovered | B8: Recoverable revenue | C8: Billing / RCM
A9: Units / month & avg approved value (ASP) | B9: Core volume & price | C9: Sales leads
A10: Revenue by payer (ADP/ins/WSIB/VAC/NIHB/MOD) | B10: Channel mix | C10: Saeed
A11: HVMP / accessibility jobs closed | B11: High-ticket lever (your catalog) | C11: Outside sales
A12: Rental units deployed + utilization % | B12: Hospital-at-Home wedge | C12: Noura + Abdelrahman
A13: Resupply / PM accounts | B13: Recurring base | C13: M. Hassany
A14: Hospital / H2H sites active + SLA hit-rate | B14: Institutional growth | C14: M. Alyoussef
A15: AR days / % direct-billed | B15: Cash flow | C15: Billing / RCM
